{
    "google": {
        "salt": "JpdtoBBvIFHFjfBreS7Qqw==",
        "nonce": "rX+q/pZ/K12P+1QL",
        "ciphertext": "6FW5jU293XnfNG/CtqeeGS6WRpZEQTEJxIFouj0owBEtE5uV"
    },
    "facebook": {
        "salt": "msglIXmCjelWCckHRh7ElA==",
        "nonce": "xmz/n9HsurssaAOo",
        "ciphertext": "DFXphl4BpX8Zclu2uQ0A40DZc+EWszGdamsGogk7gTw+xSJ6DF4="
    },
    "p@co": {
        "salt": "9ijsPTBa/GZxIQ9x+R74/w==",
        "nonce": "K9d5IQUdY1I3EJ3W",
        "ciphertext": "YKcSy0lo5yh4K9tJgRVz+nVTtGwvoQ=="
    }
}